README.md
setup.cfg
setup.py
allrank_mod/__init__.py
allrank_mod/config.py
allrank_mod/main.py
allrank_mod/rank_and_click.py
allrank_mod.egg-info/PKG-INFO
allrank_mod.egg-info/SOURCES.txt
allrank_mod.egg-info/dependency_links.txt
allrank_mod.egg-info/entry_points.txt
allrank_mod.egg-info/not-zip-safe
allrank_mod.egg-info/top_level.txt
allrank_mod/click_models/__init__.py
allrank_mod/click_models/base.py
allrank_mod/click_models/cascade_models.py
allrank_mod/click_models/click_utils.py
allrank_mod/click_models/duplicate_aware.py
allrank_mod/data/__init__.py
allrank_mod/data/dataset_loading.py
allrank_mod/data/dataset_saving.py
allrank_mod/data/generate_dummy_data.py
allrank_mod/inference/__init__.py
allrank_mod/inference/inference_utils.py
allrank_mod/models/__init__.py
allrank_mod/models/metrics.py
allrank_mod/models/model.py
allrank_mod/models/model_utils.py
allrank_mod/models/positional.py
allrank_mod/models/transformer.py
allrank_mod/models/losses/__init__.py
allrank_mod/models/losses/approxNDCG.py
allrank_mod/models/losses/bce.py
allrank_mod/models/losses/binary_listNet.py
allrank_mod/models/losses/lambdaLoss.py
allrank_mod/models/losses/listMLE.py
allrank_mod/models/losses/listNet.py
allrank_mod/models/losses/ordinal.py
allrank_mod/models/losses/pointwise.py
allrank_mod/models/losses/rankNet.py
allrank_mod/training/__init__.py
allrank_mod/training/early_stop.py
allrank_mod/training/train_utils.py
allrank_mod/utils/__init__.py
allrank_mod/utils/args_utils.py
allrank_mod/utils/command_executor.py
allrank_mod/utils/config_utils.py
allrank_mod/utils/experiments.py
allrank_mod/utils/file_utils.py
allrank_mod/utils/ltr_logging.py
allrank_mod/utils/python_utils.py
allrank_mod/utils/tensorboard_utils.py
tests/click_models/__init__.py
tests/click_models/test_alternative_click_models.py
tests/click_models/test_apply_click_model.py
tests/click_models/test_base_cascade_model.py
tests/click_models/test_diverse_clicks_model.py
tests/click_models/test_duplicate_click_model.py
tests/click_models/test_feature_click_model.py
tests/click_models/test_fixed_click_model.py
tests/click_models/test_masked_click_model.py
tests/click_models/test_random_click_model.py
tests/losses/__init__.py
