Metadata-Version: 2.1
Name: allrank-mod
Version: 1.3.0a0
Summary: allRank is a framework for training learning-to-rank neural models
Home-page: https://github.com/allegro/allRank
Author-email: allrank@allegro.pl
License: Apache 2
Platform: UNKNOWN
